{
  "setting": "",
  "comment": "2x2-maze-spin-random-0-1-2",
  "back_color": 200,
  "room_name": "VideoKit-Room-1",
  "patch_layout": "2x2",
  "canvas_size": "640x480",
  "capture_size": "default",
  "render_size": "Canvas",
  "chat_name": "jht",
  "chat_chk": 0,
  "live_index": 0,
  "live_chk": 0,
  "urects_lock": 0,
  "urects_count": 4,
  "canvas_resize_ref": "",
  "canvas_data_chk": 0,
  "mediaDiv_states": [
    null,
    {
      "vis": 0,
      "mute": 1
    }
  ],
  "patches": [
    {
      "eff_spec": {
        "ipatch": 0,
        "imedia": 1,
        "eff_label": "maze_spin",
        "urect": {
          "x0": 0,
          "y0": 0,
          "width": 320,
          "height": 240
        }
      },
      "eff_props": {
        "ncells": 31,
        "strokeWeight": 0.5,
        "delta": 1,
        "do_spiral": 0,
        "do_random": 0,
        "do_report": 0,
        "step_period": 1,
        "pause_period": 1,
        "video_color": 1,
        "do_cycle": 0
      }
    },
    {
      "eff_spec": {
        "ipatch": 1,
        "imedia": 1,
        "eff_label": "maze_spin",
        "urect": {
          "x0": 320,
          "y0": 0,
          "width": 320,
          "height": 240
        }
      },
      "eff_props": {
        "ncells": 31,
        "strokeWeight": 0.5,
        "delta": 1,
        "do_spiral": 1,
        "do_random": 0,
        "do_report": 0,
        "step_period": 1,
        "pause_period": 1,
        "video_color": 1,
        "do_cycle": 0
      }
    },
    {
      "eff_spec": {
        "ipatch": 2,
        "imedia": 1,
        "eff_label": "maze_spin",
        "urect": {
          "x0": 0,
          "y0": 240,
          "width": 320,
          "height": 240
        }
      },
      "eff_props": {
        "ncells": 31,
        "strokeWeight": 0.5,
        "delta": 1,
        "do_spiral": 1,
        "do_random": 1,
        "do_report": 0,
        "step_period": 1,
        "pause_period": 1,
        "video_color": 1,
        "do_cycle": 1
      }
    },
    {
      "eff_spec": {
        "ipatch": 3,
        "imedia": 1,
        "eff_label": "maze_spin",
        "urect": {
          "x0": 320,
          "y0": 240,
          "width": 320,
          "height": 240
        }
      },
      "eff_props": {
        "ncells": 31,
        "strokeWeight": 0.5,
        "delta": 1,
        "do_spiral": 1,
        "do_random": 2,
        "do_report": 0,
        "step_period": 1,
        "pause_period": 1,
        "video_color": 1,
        "do_cycle": 2
      }
    }
  ]
}
